{
  "text_logic_form": [
    "Find(AreaOf(Shape($)))"
  ],
  "dissolved_text_logic_form": [
    "Find(AreaOf(Polygon(A,E,C,B,D,I)))"
  ],
  "diagram_logic_form": [
    "Equals(LengthOf(Line(A, E)), 23)",
    "Equals(LengthOf(Line(I, F)), 10)",
    "Equals(LengthOf(Line(I, C)), 8)",
    "Equals(LengthOf(Line(I, G)), 10)",
    "Equals(LengthOf(Line(B, D)), 23)",
    "PointLiesOnLine(F, Line(A, E))",
    "PointLiesOnLine(G, Line(B, D))",
    "Perpendicular(Line(I, F), Line(A, F))",
    "Perpendicular(Line(I, G), Line(D, G))"
  ],
  "line_instances": [
    "AE",
    "AI",
    "BC",
    "BD",
    "EC",
    "IC",
    "ID",
    "IF",
    "IG",
    "AF",
    "EF",
    "DG",
    "BG",
    ""
  ],
  "point_positions": {
    "A": [
      1.0,
      2.0
    ],
    "B": [
      219.0,
      192.0
    ],
    "C": [
      148.0,
      96.0
    ],
    "D": [
      2.0,
      192.0
    ],
    "E": [
      220.0,
      2.0
    ],
    "I": [
      73.0,
      99.0
    ]
  },
  "circle_instances": [
    ""
  ]
}