{
  "text_logic_form": [
    "Find(AreaOf(Shape($)))"
  ],
  "dissolved_text_logic_form": [
    "Find(AreaOf(Triangle(A,C,B)))"
  ],
  "diagram_logic_form": [
    "Equals(LengthOf(Line(A, B)), 26)",
    "Equals(LengthOf(Line(A, D)), 10)",
    "Equals(LengthOf(Line(D, C)), 8)",
    "Equals(LengthOf(Line(B, C)), 16)",
    "PointLiesOnLine(C, Line(B, D))",
    "Perpendicular(Line(A, D), Line(D, C))"
  ],
  "line_instances": [
    "AB",
    "AC",
    "AD",
    "BC",
    "BD",
    "DC"
  ],
  "point_positions": {
    "A": [
      1.0,
      1.0
    ],
    "B": [
      183.0,
      86.0
    ],
    "C": [
      66.0,
      86.0
    ]
  },
  "circle_instances": [
    ""
  ]
}